MANIFEST.in
README.md
setup.py
studygroups/__init__.py
studygroups/admin.py
studygroups/app_registry.py
studygroups/feeds.py
studygroups/forms.py
studygroups/managers.py
studygroups/models.py
studygroups/module_meta.py
studygroups/search_indexes.py
studygroups/urls.py
studygroups/views.py
studygroups/migrations/0001_initial.py
studygroups/migrations/0002_auto__add_field_position_group.py
studygroups/migrations/__init__.py
studygroups/static/chosen/chosen-sprite.png
studygroups/static/chosen/chosen.css
studygroups/static/chosen/chosen.jquery.min.js
studygroups/templates/nexus/base.html
studygroups/templates/search/indexes/studygroups/studygroup_text.txt
studygroups/templates/studygroups/add.html
studygroups/templates/studygroups/base.html
studygroups/templates/studygroups/delete.html
studygroups/templates/studygroups/detail.html
studygroups/templates/studygroups/edit-meta.html
studygroups/templates/studygroups/edit.html
studygroups/templates/studygroups/form.html
studygroups/templates/studygroups/meta.html
studygroups/templates/studygroups/nav.html
studygroups/templates/studygroups/officer-formset.html
studygroups/templates/studygroups/options.html
studygroups/templates/studygroups/search-form.html
studygroups/templates/studygroups/search-result.html
studygroups/templates/studygroups/search.html
studygroups/templates/studygroups/media/css/studygroups.css
studygroups/templatetags/__init__.py
studygroups/templatetags/studygroup_tags.py
tendenci_studygroups.egg-info/PKG-INFO
tendenci_studygroups.egg-info/SOURCES.txt
tendenci_studygroups.egg-info/dependency_links.txt
tendenci_studygroups.egg-info/requires.txt
tendenci_studygroups.egg-info/top_level.txt